Metadata-Version: 2.1
Name: TrajAtlas
Version: 0.3.2
Summary: TrajAtlas, a trajectory-centric framework reveals differentiation heterogenity among cells, genes, and gene modules
Author-email: Gilbert Han <gilberthan1011@gmail.com>
Project-URL: Homepage, https://github.com/GilbertHan1011/TrajAtlas
Project-URL: Bug Tracker, https://github.com/GilbertHan1011/TrajAtlas/issues
Classifier: Programming Language :: Python :: 3
Classifier: License :: OSI Approved :: MIT License
Classifier: Operating System :: OS Independent
Requires-Python: >=3.8
License-File: LICENSE
Requires-Dist: anndata >=0.8.0
Requires-Dist: numpy >=1.23.5
Requires-Dist: scipy >=1.10.1
Requires-Dist: joblib >=1.2.0
Requires-Dist: pandas <2.0.0
Requires-Dist: scvi >=0.6.8
Requires-Dist: scanpy >=1.9.1
Requires-Dist: mudata >=0.2.3
Requires-Dist: tqdm >=4.65.0
Requires-Dist: statsmodels >=0.14.0
Requires-Dist: PyComplexHeatmap >=1.6.4
Requires-Dist: lightgbm
Requires-Dist: scikit-learn
Requires-Dist: rich
Requires-Dist: muon
Requires-Dist: docrep
Requires-Dist: rpy2
Requires-Dist: optax ==0.1.5
Provides-Extra: scarches
Requires-Dist: scarches >=0.5.6 ; extra == 'scarches'
Requires-Dist: tensorflow >=2.13.0 ; extra == 'scarches'
